langchain_chatopera/__init__.py
langchain_chatopera/api_wrapper.py
langchain_chatopera/tool.py
langchain_chatopera-0.0.3.dist-info/licenses/LICENSE
langchain_chatopera-0.0.3.dist-info/METADATA
langchain_chatopera-0.0.3.dist-info/WHEEL
langchain_chatopera-0.0.3.dist-info/top_level.txt
langchain_chatopera-0.0.3.dist-info/RECORD
